dynamic_sarimax/__init__.py
dynamic_sarimax/config.py
dynamic_sarimax/evaluation.py
dynamic_sarimax/features.py
dynamic_sarimax/metrics.py
dynamic_sarimax/model.py
dynamic_sarimax/selection.py
dynamic_sarimax/utils.py
dynamic_sarimax-1.0.0.dist-info/LICENSE
dynamic_sarimax-1.0.0.dist-info/METADATA
dynamic_sarimax-1.0.0.dist-info/WHEEL
dynamic_sarimax-1.0.0.dist-info/RECORD
