Metadata-Version: 2.1
Name: dynamic-sarimax
Version: 1.0.0
Summary: Safe, delay-aware SARIMAX with rolling evaluation and AIC-based lag selection
Home-page: https://github.com/NefariousNiru/dynamic-sarimax
License: Apache-2.0
Keywords: time-series,sarimax,arima,forecasting,exogenous
Author: Nirupom Bose Roy
Author-email: nirupomboseroy@uga.edu
Requires-Python: >=3.12,<4.0
Classifier: Intended Audience :: Science/Research
Classifier: License :: OSI Approved :: Apache Software License
Classifier: Operating System :: OS Independent
Classifier: Programming Language :: Python :: 3
Classifier: Programming Language :: Python :: 3.12
Classifier: Programming Language :: Python :: 3.13
Classifier: Programming Language :: Python :: 3.10
Classifier: Programming Language :: Python :: 3.11
Classifier: Topic :: Scientific/Engineering :: Information Analysis
Requires-Dist: matplotlib (>=3.10.7,<4.0.0)
Requires-Dist: numpy (>=2.3.3,<3.0.0)
Requires-Dist: pandas (>=2.3.3,<3.0.0)
Requires-Dist: statsmodels (>=0.14.5,<0.15.0)
Project-URL: Repository, https://github.com/NefariousNiru/dynamic-sarimax
